{"cameraMode":{"drawMode":0,"name":"Shaded","section":"Shading Mode"},"sceneLighting":true,"audioPlay":false,"sceneViewState":{"showFog":true,"showMaterialUpdate":false,"showSkybox":true,"showFlares":true,"showImageEffects":true,"showParticleSystems":true},"in2DMode":false,"pivot":{"x":1.0697814226150513,"y":4.465726852416992,"z":-5.628177165985107},"rotation":{"x":0.3204801082611084,"y":-0.029835116118192674,"z":0.010090850293636322,"w":0.9467503428459168},"size":27.066207885742189,"orthographic":false}